[
  {
    "id": "chaos",
    "name": "Chaos Orb",
    "chaosValue": 1,
    "fetchedAt": "2026-03-05T09:12:30.776Z"
  },
  {
    "id": "scour",
    "name": "Orb of Scouring",
    "chaosValue": 0.1222,
    "fetchedAt": "2026-03-05T09:12:30.776Z"
  },
  {
    "id": "divine",
    "name": "Divine Orb",
    "chaosValue": 731.2,
    "fetchedAt": "2026-03-05T09:12:30.776Z"
  },
  {
    "id": "abrasive-catalyst",
    "name": "Abrasive Catalyst",
    "chaosValue": 5,
    "fetchedAt": "2026-03-05T09:12:30.776Z"
  },
  {
    "id": "eldritch-chaos-orb",
    "name": "Eldritch Chaos Orb",
    "chaosValue": 150.2,
    "fetchedAt": "2026-03-05T09:12:30.776Z"
  },
  {
    "id": "explorers-scouting-report",
    "name": "Explorer's Scouting Report",
    "chaosValue": 7.38,
    "fetchedAt": "2026-03-05T09:12:30.776Z"
  },
  {
    "id": "orb-of-unmaking",
    "name": "Orb of Unmaking",
    "chaosValue": 0.0779,
    "fetchedAt": "2026-03-05T09:12:30.776Z"
  },
  {
    "id": "veiled-chaos-orb",
    "name": "Veiled Chaos Orb",
    "chaosValue": 165.9,
    "fetchedAt": "2026-03-05T09:12:30.776Z"
  },
  {
    "id": "aug",
    "name": "Orb of Augmentation",
    "chaosValue": 0.0004207,
    "fetchedAt": "2026-03-05T09:12:30.776Z"
  },
  {
    "id": "orb-of-conflict",
    "name": "Orb of Conflict",
    "chaosValue": 1394,
    "fetchedAt": "2026-03-05T09:12:30.776Z"
  },
  {
    "id": "orb-of-remembrance",
    "name": "Orb of Remembrance",
    "chaosValue": 2648,
    "fetchedAt": "2026-03-05T09:12:30.776Z"
  },
  {
    "id": "vaal",
    "name": "Vaal Orb",
    "chaosValue": 1.22,
    "fetchedAt": "2026-03-05T09:12:30.776Z"
  },
  {
    "id": "alch",
    "name": "Orb of Alchemy",
    "chaosValue": 0.000759,
    "fetchedAt": "2026-03-05T09:12:30.776Z"
  },
  {
    "id": "alt",
    "name": "Orb of Alteration",
    "chaosValue": 0.0138,
    "fetchedAt": "2026-03-05T09:12:30.776Z"
  },
  {
    "id": "wisdom",
    "name": "Scroll of Wisdom",
    "chaosValue": 0.0001908,
    "fetchedAt": "2026-03-05T09:12:30.776Z"
  },
  {
    "id": "mavens-chisel-of-avarice",
    "name": "Maven's Chisel of Avarice",
    "chaosValue": 279.5,
    "fetchedAt": "2026-03-05T09:12:30.776Z"
  },
  {
    "id": "tainted-orb-of-fusing",
    "name": "Tainted Orb of Fusing",
    "chaosValue": 61.79,
    "fetchedAt": "2026-03-05T09:12:30.776Z"
  },
  {
    "id": "gcp",
    "name": "Gemcutter's Prism",
    "chaosValue": 4.86,
    "fetchedAt": "2026-03-05T09:12:30.776Z"
  },
  {
    "id": "instilling-orb",
    "name": "Instilling Orb",
    "chaosValue": 0.01921,
    "fetchedAt": "2026-03-05T09:12:30.776Z"
  },
  {
    "id": "chisel",
    "name": "Cartographer's Chisel",
    "chaosValue": 0.981,
    "fetchedAt": "2026-03-05T09:12:30.776Z"
  },
  {
    "id": "tainted-chromatic-orb",
    "name": "Tainted Chromatic Orb",
    "chaosValue": 24.49,
    "fetchedAt": "2026-03-05T09:12:30.776Z"
  },
  {
    "id": "vivid-lifeforce",
    "name": "Vivid Crystallised Lifeforce",
    "chaosValue": 0.4308,
    "fetchedAt": "2026-03-05T09:12:30.776Z"
  },
  {
    "id": "mavens-orb",
    "name": "Orb of Dominance",
    "chaosValue": 4026,
    "fetchedAt": "2026-03-05T09:12:30.776Z"
  },
  {
    "id": "wild-lifeforce",
    "name": "Wild Crystallised Lifeforce",
    "chaosValue": 0.1086,
    "fetchedAt": "2026-03-05T09:12:30.776Z"
  },
  {
    "id": "vaal-scouting-report",
    "name": "Vaal Scouting Report",
    "chaosValue": 4.91,
    "fetchedAt": "2026-03-05T09:12:30.776Z"
  },
  {
    "id": "enkindling-orb",
    "name": "Enkindling Orb",
    "chaosValue": 0.9112,
    "fetchedAt": "2026-03-05T09:12:30.776Z"
  },
  {
    "id": "grand-eldritch-ichor",
    "name": "Grand Eldritch Ichor",
    "chaosValue": 12.84,
    "fetchedAt": "2026-03-05T09:12:30.776Z"
  },
  {
    "id": "exceptional-eldritch-ember",
    "name": "Exceptional Eldritch Ember",
    "chaosValue": 1437,
    "fetchedAt": "2026-03-05T09:12:30.776Z"
  },
  {
    "id": "shapers-exalted-orb",
    "name": "Shaper's Exalted Orb",
    "chaosValue": 1280,
    "fetchedAt": "2026-03-05T09:12:30.776Z"
  },
  {
    "id": "primal-lifeforce",
    "name": "Primal Crystallised Lifeforce",
    "chaosValue": 0.11,
    "fetchedAt": "2026-03-05T09:12:30.776Z"
  },
  {
    "id": "warlords-exalted-orb",
    "name": "Warlord's Exalted Orb",
    "chaosValue": 2388,
    "fetchedAt": "2026-03-05T09:12:30.776Z"
  },
  {
    "id": "lesser-eldritch-ember",
    "name": "Lesser Eldritch Ember",
    "chaosValue": 0.325,
    "fetchedAt": "2026-03-05T09:12:30.776Z"
  },
  {
    "id": "fracturing-orb",
    "name": "Fracturing Orb",
    "chaosValue": 4336,
    "fetchedAt": "2026-03-05T09:12:30.776Z"
  },
  {
    "id": "mavens-chisel-of-scarabs",
    "name": "Maven's Chisel of Scarabs",
    "chaosValue": 124.8,
    "fetchedAt": "2026-03-05T09:12:30.776Z"
  },
  {
    "id": "ancient-shard",
    "name": "Ancient Shard",
    "chaosValue": 2,
    "fetchedAt": "2026-03-05T09:12:30.776Z"
  },
  {
    "id": "regal",
    "name": "Regal Orb",
    "chaosValue": 0.01922,
    "fetchedAt": "2026-03-05T09:12:30.776Z"
  },
  {
    "id": "harbingers-orb",
    "name": "Harbinger's Orb",
    "chaosValue": 1.76,
    "fetchedAt": "2026-03-05T09:12:30.776Z"
  },
  {
    "id": "unstable-catalyst",
    "name": "Unstable Catalyst",
    "chaosValue": 30.46,
    "fetchedAt": "2026-03-05T09:12:30.776Z"
  },
  {
    "id": "eldritch-exalted-orb",
    "name": "Eldritch Exalted Orb",
    "chaosValue": 63,
    "fetchedAt": "2026-03-05T09:12:30.776Z"
  },
  {
    "id": "lesser-eldritch-ichor",
    "name": "Lesser Eldritch Ichor",
    "chaosValue": 0.2659,
    "fetchedAt": "2026-03-05T09:12:30.776Z"
  },
  {
    "id": "mavens-chisel-of-procurement",
    "name": "Maven's Chisel of Procurement",
    "chaosValue": 17.83,
    "fetchedAt": "2026-03-05T09:12:30.776Z"
  },
  {
    "id": "exceptional-eldritch-ichor",
    "name": "Exceptional Eldritch Ichor",
    "chaosValue": 1638,
    "fetchedAt": "2026-03-05T09:12:30.776Z"
  },
  {
    "id": "elders-exalted-orb",
    "name": "Elder's Exalted Orb",
    "chaosValue": 568.7,
    "fetchedAt": "2026-03-05T09:12:30.776Z"
  },
  {
    "id": "chrome",
    "name": "Chromatic Orb",
    "chaosValue": 0.2918,
    "fetchedAt": "2026-03-05T09:12:30.776Z"
  },
  {
    "id": "portal",
    "name": "Portal Scroll",
    "chaosValue": 0.001229,
    "fetchedAt": "2026-03-05T09:12:30.776Z"
  },
  {
    "id": "regret",
    "name": "Orb of Regret",
    "chaosValue": 1.24,
    "fetchedAt": "2026-03-05T09:12:30.776Z"
  },
  {
    "id": "crusaders-exalted-orb",
    "name": "Crusader's Exalted Orb",
    "chaosValue": 1097,
    "fetchedAt": "2026-03-05T09:12:30.776Z"
  },
  {
    "id": "chance",
    "name": "Orb of Chance",
    "chaosValue": 0.01002,
    "fetchedAt": "2026-03-05T09:12:30.776Z"
  },
  {
    "id": "eldritch-orb-of-annulment",
    "name": "Eldritch Orb of Annulment",
    "chaosValue": 99.03,
    "fetchedAt": "2026-03-05T09:12:30.776Z"
  },
  {
    "id": "tainted-chaos-orb",
    "name": "Tainted Chaos Orb",
    "chaosValue": 103.1,
    "fetchedAt": "2026-03-05T09:12:30.776Z"
  },
  {
    "id": "regal-implant",
    "name": "Regal Implant",
    "chaosValue": 150.2,
    "fetchedAt": "2026-03-05T04:09:15.244Z"
  },
  {
    "id": "augmentation-implant",
    "name": "Augmentation Implant",
    "chaosValue": 150.2,
    "fetchedAt": "2026-03-05T04:09:15.244Z"
  },
  {
    "id": "grand-eldritch-ember",
    "name": "Grand Eldritch Ember",
    "chaosValue": 66.53,
    "fetchedAt": "2026-03-05T09:12:30.776Z"
  },
  {
    "id": "stacked-deck",
    "name": "Stacked Deck",
    "chaosValue": 14.1,
    "fetchedAt": "2026-03-05T09:12:30.776Z"
  },
  {
    "id": "redeemers-exalted-orb",
    "name": "Redeemer's Exalted Orb",
    "chaosValue": 731.2,
    "fetchedAt": "2026-03-05T09:12:30.776Z"
  },
  {
    "id": "foulborn-regal-orb",
    "name": "Foulborn Regal Orb",
    "chaosValue": 146.2,
    "fetchedAt": "2026-03-05T09:12:30.776Z"
  },
  {
    "id": "tailoring-orb",
    "name": "Tailoring Orb",
    "chaosValue": 3161,
    "fetchedAt": "2026-03-05T09:12:30.776Z"
  },
  {
    "id": "awakeners-orb",
    "name": "Awakener's Orb",
    "chaosValue": 1401,
    "fetchedAt": "2026-03-05T09:12:30.776Z"
  },
  {
    "id": "rogues-marker",
    "name": "Rogue's Marker",
    "chaosValue": 0.00009585,
    "fetchedAt": "2026-03-05T09:12:30.776Z"
  },
  {
    "id": "mavens-chisel-of-proliferation",
    "name": "Maven's Chisel of Proliferation",
    "chaosValue": 228,
    "fetchedAt": "2026-03-05T09:12:30.776Z"
  },
  {
    "id": "accelerating-catalyst",
    "name": "Accelerating Catalyst",
    "chaosValue": 20.6,
    "fetchedAt": "2026-03-05T09:12:30.776Z"
  },
  {
    "id": "intrinsic-catalyst",
    "name": "Intrinsic Catalyst",
    "chaosValue": 9.93,
    "fetchedAt": "2026-03-05T09:12:30.776Z"
  },
  {
    "id": "delirious-scouting-report",
    "name": "Delirious Scouting Report",
    "chaosValue": 0.5,
    "fetchedAt": "2026-03-05T09:12:30.776Z"
  },
  {
    "id": "greater-eldritch-ichor",
    "name": "Greater Eldritch Ichor",
    "chaosValue": 1.65,
    "fetchedAt": "2026-03-05T09:12:30.776Z"
  },
  {
    "id": "fracturing-shard",
    "name": "Fracturing Shard",
    "chaosValue": 208.9,
    "fetchedAt": "2026-03-05T09:12:30.776Z"
  },
  {
    "id": "tainted-mythic-orb",
    "name": "Tainted Mythic Orb",
    "chaosValue": 35.03,
    "fetchedAt": "2026-03-05T09:12:30.776Z"
  },
  {
    "id": "tainted-divine-teardrop",
    "name": "Tainted Divine Teardrop",
    "chaosValue": 13886,
    "fetchedAt": "2026-03-05T09:12:30.776Z"
  },
  {
    "id": "tainted-jewellers-orb",
    "name": "Tainted Jeweller's Orb",
    "chaosValue": 4.87,
    "fetchedAt": "2026-03-05T09:12:30.776Z"
  },
  {
    "id": "bauble",
    "name": "Glassblower's Bauble",
    "chaosValue": 0.1377,
    "fetchedAt": "2026-03-05T09:12:30.776Z"
  },
  {
    "id": "mavens-chisel-of-divination",
    "name": "Maven's Chisel of Divination",
    "chaosValue": 52.6,
    "fetchedAt": "2026-03-05T09:12:30.776Z"
  },
  {
    "id": "whetstone",
    "name": "Blacksmith's Whetstone",
    "chaosValue": 0.0003137,
    "fetchedAt": "2026-03-05T09:12:30.776Z"
  },
  {
    "id": "mirror",
    "name": "Mirror of Kalandra",
    "chaosValue": 1299865,
    "fetchedAt": "2026-03-05T09:12:30.776Z"
  },
  {
    "id": "fusing",
    "name": "Orb of Fusing",
    "chaosValue": 0.6142,
    "fetchedAt": "2026-03-05T09:12:30.776Z"
  },
  {
    "id": "reflecting-mist",
    "name": "Reflecting Mist",
    "chaosValue": 22806,
    "fetchedAt": "2026-03-05T09:12:30.776Z"
  },
  {
    "id": "tempering-orb",
    "name": "Tempering Orb",
    "chaosValue": 2603,
    "fetchedAt": "2026-03-05T09:12:30.776Z"
  },
  {
    "id": "jewellers",
    "name": "Jeweller's Orb",
    "chaosValue": 0.01034,
    "fetchedAt": "2026-03-05T09:12:30.776Z"
  },
  {
    "id": "noxious-catalyst",
    "name": "Noxious Catalyst",
    "chaosValue": 11.74,
    "fetchedAt": "2026-03-05T09:12:30.776Z"
  },
  {
    "id": "tainted-armourers-scrap",
    "name": "Tainted Armourer's Scrap",
    "chaosValue": 0.125,
    "fetchedAt": "2026-03-05T09:12:30.776Z"
  },
  {
    "id": "exalted",
    "name": "Exalted Orb",
    "chaosValue": 57.39,
    "fetchedAt": "2026-03-05T09:12:30.776Z"
  },
  {
    "id": "tainted-exalted-orb",
    "name": "Tainted Exalted Orb",
    "chaosValue": 843.6,
    "fetchedAt": "2026-03-05T09:12:30.776Z"
  },
  {
    "id": "orb-of-horizons",
    "name": "Orb of Horizons",
    "chaosValue": 0.02202,
    "fetchedAt": "2026-03-05T09:12:30.776Z"
  },
  {
    "id": "hinekoras-lock",
    "name": "Hinekora's Lock",
    "chaosValue": 289307,
    "fetchedAt": "2026-03-05T09:12:30.776Z"
  },
  {
    "id": "influenced-scouting-report",
    "name": "Influenced Scouting Report",
    "chaosValue": 1.87,
    "fetchedAt": "2026-03-05T09:12:30.776Z"
  },
  {
    "id": "orb-of-unravelling",
    "name": "Orb of Unravelling",
    "chaosValue": 731.2,
    "fetchedAt": "2026-03-05T09:12:30.776Z"
  },
  {
    "id": "transmute",
    "name": "Orb of Transmutation",
    "chaosValue": 0.00006458,
    "fetchedAt": "2026-03-05T09:12:30.776Z"
  },
  {
    "id": "scrap",
    "name": "Armourer's Scrap",
    "chaosValue": 0.0009622,
    "fetchedAt": "2026-03-05T09:12:30.776Z"
  },
  {
    "id": "mirror-shard",
    "name": "Mirror Shard",
    "chaosValue": 65780,
    "fetchedAt": "2026-03-05T09:12:30.776Z"
  },
  {
    "id": "ancient-orb",
    "name": "Ancient Orb",
    "chaosValue": 63.33,
    "fetchedAt": "2026-03-05T09:12:30.776Z"
  },
  {
    "id": "prismatic-catalyst",
    "name": "Prismatic Catalyst",
    "chaosValue": 67.3,
    "fetchedAt": "2026-03-05T09:12:30.776Z"
  },
  {
    "id": "fertile-catalyst",
    "name": "Fertile Catalyst",
    "chaosValue": 81.24,
    "fetchedAt": "2026-03-05T09:12:30.776Z"
  },
  {
    "id": "foulborn-orb-of-augmentation",
    "name": "Foulborn Orb of Augmentation",
    "chaosValue": 2.2,
    "fetchedAt": "2026-03-05T09:12:30.776Z"
  },
  {
    "id": "operatives-scouting-report",
    "name": "Operative's Scouting Report",
    "chaosValue": 4.92,
    "fetchedAt": "2026-03-05T07:10:04.902Z"
  },
  {
    "id": "imbued-catalyst",
    "name": "Imbued Catalyst",
    "chaosValue": 3.18,
    "fetchedAt": "2026-03-05T09:12:30.776Z"
  },
  {
    "id": "blessed",
    "name": "Blessed Orb",
    "chaosValue": 0.05408,
    "fetchedAt": "2026-03-05T09:12:30.776Z"
  },
  {
    "id": "tainted-blacksmiths-whetstone",
    "name": "Tainted Blacksmith's Whetstone",
    "chaosValue": 19.44,
    "fetchedAt": "2026-03-05T09:12:30.776Z"
  },
  {
    "id": "engineers-shard",
    "name": "Engineer's Shard",
    "chaosValue": 0.125,
    "fetchedAt": "2026-03-04T23:56:24.993Z"
  },
  {
    "id": "comprehensive-scouting-report",
    "name": "Comprehensive Scouting Report",
    "chaosValue": 2.37,
    "fetchedAt": "2026-03-05T09:12:30.776Z"
  },
  {
    "id": "annul",
    "name": "Orb of Annulment",
    "chaosValue": 19.11,
    "fetchedAt": "2026-03-05T09:12:30.776Z"
  },
  {
    "id": "foulborn-exalted-orb",
    "name": "Foulborn Exalted Orb",
    "chaosValue": 5910,
    "fetchedAt": "2026-03-05T09:12:30.776Z"
  },
  {
    "id": "orb-of-intention",
    "name": "Orb of Intention",
    "chaosValue": 300,
    "fetchedAt": "2026-03-05T09:12:30.776Z"
  },
  {
    "id": "greater-eldritch-ember",
    "name": "Greater Eldritch Ember",
    "chaosValue": 9.47,
    "fetchedAt": "2026-03-05T09:12:30.776Z"
  },
  {
    "id": "tainted-catalyst",
    "name": "Tainted Catalyst",
    "chaosValue": 113.7,
    "fetchedAt": "2026-03-05T09:12:30.776Z"
  },
  {
    "id": "sacred-orb",
    "name": "Sacred Orb",
    "chaosValue": 127.9,
    "fetchedAt": "2026-03-05T09:12:30.776Z"
  },
  {
    "id": "veiled-exalted-orb",
    "name": "Veiled Exalted Orb",
    "chaosValue": 105.1,
    "fetchedAt": "2026-03-05T09:12:30.776Z"
  },
  {
    "id": "sacred-lifeforce",
    "name": "Sacred Crystallised Lifeforce",
    "chaosValue": 1024,
    "fetchedAt": "2026-03-05T09:12:30.776Z"
  },
  {
    "id": "singular-scouting-report",
    "name": "Singular Scouting Report",
    "chaosValue": 0.9413,
    "fetchedAt": "2026-03-05T09:12:30.776Z"
  },
  {
    "id": "hunters-exalted-orb",
    "name": "Hunter's Exalted Orb",
    "chaosValue": 1985,
    "fetchedAt": "2026-03-05T09:12:30.776Z"
  },
  {
    "id": "turbulent-catalyst",
    "name": "Turbulent Catalyst",
    "chaosValue": 16.96,
    "fetchedAt": "2026-03-05T09:12:30.776Z"
  },
  {
    "id": "tempering-catalyst",
    "name": "Tempering Catalyst",
    "chaosValue": 24.78,
    "fetchedAt": "2026-03-05T09:12:30.776Z"
  },
  {
    "id": "blighted-scouting-report",
    "name": "Blighted Scouting Report",
    "chaosValue": 1,
    "fetchedAt": "2026-03-05T07:10:04.902Z"
  },
  {
    "id": "otherworldly-scouting-report",
    "name": "Otherworldly Scouting Report",
    "chaosValue": 3.12,
    "fetchedAt": "2026-03-05T09:12:30.776Z"
  },
  {
    "id": "horizon-shard",
    "name": "Horizon Shard",
    "chaosValue": 1,
    "fetchedAt": "2026-03-04T15:01:59.104Z"
  },
  {
    "id": "engineers",
    "name": "Engineer's Orb",
    "chaosValue": 1.4,
    "fetchedAt": "2026-03-05T09:12:30.776Z"
  },
  {
    "id": "exalted-shard",
    "name": "Exalted Shard",
    "chaosValue": 1,
    "fetchedAt": "2026-03-05T09:12:30.776Z"
  },
  {
    "id": "annulment-shard",
    "name": "Annulment Shard",
    "chaosValue": 1,
    "fetchedAt": "2026-03-05T03:08:21.460Z"
  },
  {
    "id": "orb-of-binding",
    "name": "Orb of Binding",
    "chaosValue": 0.1219,
    "fetchedAt": "2026-03-05T09:12:30.776Z"
  }
]